liveconfig/__init__.py
liveconfig/core.py
liveconfig/decorators.py
liveconfig/liveconfig.py
liveconfig/livevariable.py
liveconfig/manager.py
liveconfig/registration.py
liveconfig/start_interface.py
liveconfig/typechecker.py
liveconfig/interfaces/__init__.py
liveconfig/interfaces/cli/__init__.py
liveconfig/interfaces/cli/cli.py
liveconfig/interfaces/web/__init__.py
liveconfig/interfaces/web/server.py
liveconfig/interfaces/web/frontend/__init__.py
liveconfig/interfaces/web/frontend/static/__init__.py
liveconfig/interfaces/web/frontend/static/script.js
liveconfig/interfaces/web/frontend/static/style.css
liveconfig/interfaces/web/frontend/templates/__init__.py
liveconfig/interfaces/web/frontend/templates/base.html
liveconfig/interfaces/web/frontend/templates/classes.html
liveconfig/interfaces/web/frontend/templates/index.html
liveconfig/interfaces/web/frontend/templates/triggers.html
liveconfig/interfaces/web/frontend/templates/variables.html
liveconfig-0.2.1b0.dist-info/licenses/LICENSE
liveconfig-0.2.1b0.dist-info/METADATA
liveconfig-0.2.1b0.dist-info/WHEEL
liveconfig-0.2.1b0.dist-info/top_level.txt
liveconfig-0.2.1b0.dist-info/RECORD
