Metadata-Version: 2.4
Name: liveconfig
Version: 0.2.1b0
Summary: Edit variables and class instances live during runtime. CLI and web interfaces supported.
Author-email: Fergus Gault <gaultfergus@gmail.com>
License-Expression: MIT
Project-URL: Homepage, https://github.com/Fergus-Gault/LiveConfig
Classifier: Programming Language :: Python :: 3
Classifier: Operating System :: OS Independent
Classifier: Development Status :: 4 - Beta
Requires-Python: >=3.8
License-File: LICENSE
Requires-Dist: prompt_toolkit
Requires-Dist: flask
Dynamic: license-file
